cognidb/__init__.py
cognidb/clarification_handler.py
cognidb/db_connection.py
cognidb/llm_query_generator.py
cognidb/query_executor.py
cognidb/query_validator.py
cognidb/schema_fetcher.py
cognidb/user_input_processor.py
cognidb/utils.py
cognidb/databases/__init__.py
cognidb/databases/base_db.py
cognidb/databases/mysql_db.py
cognidb/databases/postgres_db.py
cognidb-0.2.5.dist-info/METADATA
cognidb-0.2.5.dist-info/WHEEL
cognidb-0.2.5.dist-info/entry_points.txt
cognidb-0.2.5.dist-info/top_level.txt
cognidb-0.2.5.dist-info/RECORD
