Metadata-Version: 2.1
Name: cognidb
Version: 0.2.5
Summary: A tool for generating SQL queries
Home-page: https://github.com/boxed-dev/cognidb
Author: Rishabh Kumar
Author-email: rishabh.vaaiv@gmail.com
Classifier: Programming Language :: Python :: 3
Classifier: License :: OSI Approved :: MIT License
Classifier: Operating System :: OS Independent
Requires-Python: >=3.6
Requires-Dist: openai
Requires-Dist: psycopg2
Requires-Dist: mysql-connector-python
Requires-Dist: sqlparse
